smindicators/__init__.py
smindicators/prepare_kline_stream_data.py
smindicators/prepare_klines_data.py
smindicators/vwap_zscore.py
smindicators-0.0.5.dist-info/METADATA
smindicators-0.0.5.dist-info/WHEEL
smindicators-0.0.5.dist-info/top_level.txt
smindicators-0.0.5.dist-info/RECORD
