Metadata-Version: 2.1
Name: smindicators
Version: 0.0.5
Summary: My Trading Indicators
Author: Mohamed Slimani
Author-email: mohamed@slimani.dev
Keywords: python,indicators,trading indicators
Classifier: Development Status :: 3 - Alpha
Classifier: Intended Audience :: Education
Classifier: Programming Language :: Python :: 3
Classifier: Operating System :: MacOS :: MacOS X
Classifier: Operating System :: Microsoft :: Windows
Requires-Dist: numpy
Requires-Dist: pandas
